api_docs_generator/__init__.py
api_docs_generator/apps.py
api_docs_generator/core/__init__.py
api_docs_generator/core/html_generator.py
api_docs_generator/core/json_generator.py
api_docs_generator/core/parser.py
api_docs_generator/core/pdf_generator.py
api_docs_generator/core/websocket_parser.py
api_docs_generator/management/__init__.py
api_docs_generator/management/commands/__init__.py
api_docs_generator/management/commands/generate_api_docs.py
drf_api_doc_generator-3.1.7.dist-info/licenses/LICENSE
drf_api_doc_generator-3.1.7.dist-info/METADATA
drf_api_doc_generator-3.1.7.dist-info/WHEEL
drf_api_doc_generator-3.1.7.dist-info/top_level.txt
drf_api_doc_generator-3.1.7.dist-info/RECORD
