Metadata-Version: 2.4
Name: drf-api-doc-generator
Version: 3.1.7
Summary: Auto-generate production-quality API & WebSocket documentation (PDF, HTML, JSON/OpenAPI) for Django REST Framework with a single command
Author-email: Ashiq <your-email@example.com>
License: MIT
Project-URL: Homepage, https://github.com/yourusername/drf-api-doc-generator
Project-URL: Documentation, https://github.com/yourusername/drf-api-doc-generator#readme
Project-URL: Repository, https://github.com/yourusername/drf-api-doc-generator
Project-URL: Issues, https://github.com/yourusername/drf-api-doc-generator/issues
Project-URL: Changelog, https://github.com/yourusername/drf-api-doc-generator/blob/main/CHANGELOG.md
Keywords: django,rest,api,documentation,swagger,openapi,pdf,drf,django-rest-framework,api-docs,auto-documentation,developer-tools,websocket,django-channels,realtime
Classifier: Development Status :: 5 - Production/Stable
Classifier: Environment :: Web Environment
Classifier: Framework :: Django
Classifier: Framework :: Django :: 3.2
Classifier: Framework :: Django :: 4.0
Classifier: Framework :: Django :: 4.1
Classifier: Framework :: Django :: 4.2
Classifier: Framework :: Django :: 5.0
Classifier: Intended Audience :: Developers
Classifier: Operating System :: OS Independent
Classifier: Programming Language :: Python
Classifier: Programming Language :: Python :: 3
Classifier: Programming Language :: Python :: 3.8
Classifier: Programming Language :: Python :: 3.9
Classifier: Programming Language :: Python :: 3.10
Classifier: Programming Language :: Python :: 3.11
Classifier: Programming Language :: Python :: 3.12
Classifier: Topic :: Documentation
Classifier: Topic :: Internet :: WWW/HTTP
Classifier: Topic :: Software Development :: Documentation
Classifier: Topic :: Software Development :: Libraries :: Python Modules
Requires-Python: >=3.8
License-File: LICENSE
Requires-Dist: Django>=3.2
Requires-Dist: djangorestframework>=3.12
Requires-Dist: reportlab>=4.0
Requires-Dist: Pillow>=9.0
Provides-Extra: dev
Requires-Dist: pytest>=7.0; extra == "dev"
Requires-Dist: pytest-django>=4.5; extra == "dev"
Requires-Dist: black>=23.0; extra == "dev"
Requires-Dist: flake8>=6.0; extra == "dev"
Requires-Dist: twine>=4.0; extra == "dev"
Requires-Dist: build>=1.0; extra == "dev"
Dynamic: license-file
